dep_laiser/__init__.py
dep_laiser/main.py
dep_laiser/matching.py
dep_laiser/run_gemini.py
dep_laiser/public/esco_embeds old.pkl
dep_laiser/public/esco_embeds.pkl
dep_laiser-1.0.4.dist-info/METADATA
dep_laiser-1.0.4.dist-info/WHEEL
dep_laiser-1.0.4.dist-info/entry_points.txt
dep_laiser-1.0.4.dist-info/top_level.txt
dep_laiser-1.0.4.dist-info/RECORD
