Metadata-Version: 2.4
Name: dep_laiser
Version: 1.0.4
Summary: Skill-extraction pipeline with Gemini + ESCO mapping
Author-email: Your Name <you@example.com>
Requires-Python: >=3.9
Requires-Dist: pandas
Requires-Dist: sentence-transformers
Requires-Dist: google-genai
Requires-Dist: torch
Requires-Dist: numpy
